KerasGA/Crossover.py
KerasGA/GeneticAlgorithm.py
KerasGA/Mutation.py
KerasGA/Selection.py
KerasGA/__init__.py
KerasGA-1.0.0.dist-info/LICENSE
KerasGA-1.0.0.dist-info/METADATA
KerasGA-1.0.0.dist-info/WHEEL
KerasGA-1.0.0.dist-info/top_level.txt
KerasGA-1.0.0.dist-info/RECORD
