Metadata-Version: 2.1
Name: KerasGA
Version: 1.0.0
Summary: A simple and easy-to-use implementation of Genetic Algorithm for Keras NN models in Python.
Home-page: https://github.com/yahiakr/KerasGA
Author: Yahia KERIM
Author-email: yahiakerim@gmail.com
License: UNKNOWN
Platform: UNKNOWN
Classifier: Programming Language :: Python :: 3
Classifier: License :: OSI Approved :: MIT License
Classifier: Operating System :: OS Independent
Requires-Python: >=3
